apium/__init__.py
apium/client.py
apium/command.py
apium/exceptions.py
apium/executor.py
apium/frameworks.py
apium/inspect.py
apium/utils.py
apium/worker.py
apium/crypt/__init__.py
apium/crypt/dh.py
apium-0.1.1.dist-info/DESCRIPTION.rst
apium-0.1.1.dist-info/METADATA
apium-0.1.1.dist-info/RECORD
apium-0.1.1.dist-info/WHEEL
apium-0.1.1.dist-info/entry_points.txt
apium-0.1.1.dist-info/metadata.json
apium-0.1.1.dist-info/pbr.json
apium-0.1.1.dist-info/top_level.txt
