Metadata-Version: 2.0
Name: apium
Version: 0.1.1
Summary: A simple remote task queue, with no dependencies.
Home-page: https://github.com/cryporchild/apium
Author: Christian Boelsen
Author-email: christianboelsen+github@gmail.com
License: LGPLv3
Keywords: celery,task,queue,job,async
Platform: UNKNOWN
Classifier: Development Status :: 4 - Beta
Classifier: Environment :: Console
Classifier: Environment :: Web Environment
Classifier: Intended Audience :: Developers
Classifier: License :: OSI Approved :: GNU Lesser General Public License v3 or later (LGPLv3+)
Classifier: Operating System :: OS Independent
Classifier: Programming Language :: Python
Classifier: Programming Language :: Python :: 2.7
Classifier: Programming Language :: Python :: 3.4
Classifier: Programming Language :: Python :: 3.5
Classifier: Programming Language :: Python :: 3.6
Requires-Dist: funcsigs (>=1.0.0); (python_version<'3')
Requires-Dist: futures (>=3.0.0); (python_version<'3')
